[
    {"project": 1, "task": 1, "user": 1},
    {"project": 1, "task": 2, "user": 1},
    {"project": 1, "task": 3, "user": 1},
    {"project": 2, "task": 4, "user": 1},
    {"project": 2, "task": 5, "user": 1},
    {"project": 2, "task": 6, "user": 1},
    {"project": 3, "task": 7, "user": 1},
    {"project": 3, "task": 8, "user": 1},
    {"project": 3, "task": 9, "user": 1},
    {"project": 4, "task": 10, "user": 1},
    {"project": 4, "task": 11, "user": 1},
    {"project": 5, "task": 12, "user": 1},
    {"project": 5, "task": 13, "user": 1},
    {"project": 5, "task": 14, "user": 1},
    {"project": 6, "task": 15, "user": 1},
    {"project": 6, "task": 16, "user": 1},
    {"project": 7, "task": 17, "user": 1},
    {"project": 7, "task": 18, "user": 1},
    {"project": 8, "task": 19, "user": 1},
    {"project": 8, "task": 20, "user": 1},
    {"project": 9, "task": 21, "user": 1},
    {"project": 9, "task": 22, "user": 1},
    {"project": 10, "task": 23, "user": 1},
    {"project": 10, "task": 24, "user": 1},
    {"project": 11, "task": 25, "user": 1},
    {"project": 11, "task": 26, "user": 1},
    {"project": 12, "task": 27, "user": 1},
    {"project": 12, "task": 28, "user": 1},
    {"project": 13, "task": 29, "user": 1},
    {"project": 13, "task": 30, "user": 1},
    {"project": 14, "task": 31, "user": 1},
    {"project": 14, "task": 32, "user": 1},
    {"project": 15, "task": 33, "user": 1},
    {"project": 15, "task": 34, "user": 1},
    {"project": 16, "task": 35, "user": 1},
    {"project": 16, "task": 36, "user": 1},
    {"project": 17, "task": 37, "user": 1},
    {"project": 17, "task": 38, "user": 1},
    {"project": 18, "task": 39, "user": 1},
    {"project": 18, "task": 40, "user": 1}
  ]
  